Workbook

Sheet Mode d'emploi
A1: Budget Famille Sans Stress
A2: Tableau de budget familial automatique : Excel, Google Sheets ou Numbers
A4: Comment ça marche, en 4 étapes
A5: 1. Onglet « Paramètres » : indiquez le mois, vos revenus et le budget prévu pour chaque catégorie.
A6: 2. Onglet « Dépenses » : notez chaque dépense (date, description, catégorie dans la liste, montant).
A7: 3. Onglet « Tableau de bord » : tout se calcule tout seul (dépensé, reste, dépassements en rouge, reste à vivre).
A8: 4. Onglet « Défi 30 jours » : cochez « Oui » chaque jour réussi et notez ce que vous avez économisé.
A10: Légende
A11: Cases jaunes = à remplir par vous. Toutes les autres cases se calculent automatiquement : ne les effacez pas.
A12: Les lignes d'exemple (en italique dans « Dépenses ») sont là pour vous montrer : supprimez-les avant de commencer.
A14: Un nouveau mois ?
A15: Faites « Fichier > Faire une copie » (Google Sheets) ou « Enregistrer sous » (Excel), puis videz l'onglet « Dépenses ».
... A18: Allez sur sheets.google.com > Fichier > Importer > Importer > choisissez ce fichier. C'est gratuit.

Sheet Paramètres
A1: Paramètres du mois
A4: Mois | B4: 46327
A5: Objectif d'épargne du mois | B5: 150
A7: Revenus | B7: Montant
A8: Salaire parent 1 | B8: 1800
A9: Salaire parent 2 | B9: 1500
A10: Allocations familiales / CAF | B10: 150
A11: Autres revenus | B11: 0
A14: Total revenus | B14: =SUM(B8:B13) -> 3450
A16: Catégorie de dépense | B16: Budget prévu | C16: Type
A17: Loyer / crédit immobilier | B17: 900 | C17: Fixe
A18: Électricité, gaz, eau | B18: 140 | C18: Fixe
A19: Internet et téléphones | B19: 50 | C19: Fixe
A20: Assurances | B20: 80 | C20: Fixe
A21: Crèche / nounou / garde | B21: 250 | C21: Fixe
A22: Cantine et périscolaire | B22: 80 | C22: Fixe
A23: Courses alimentaires | B23: 550 | C23: Variable
A24: Couches, hygiène, puériculture | B24: 60 | C24: Variable
A25: Vêtements enfants | B25: 50 | C25: Variable
A26: Activités et loisirs enfants | B26: 40 | C26: Variable
A27: Santé / pharmacie | B27: 30 | C27: Variable
A28: Transport / carburant | B28: 150 | C28: Variable
... A32: Imprévus | B32: 50 | C32: Variable
A37: Total budget prévu | B37: =SUM(B17:B36) -> 2545
A39: Les montants d'exemple sont fictifs : remplacez-les par les vôtres. 4 lignes vides sont prévues pour vos propres catégories.

Sheet Dépenses
A1: Journal des dépenses
A2: Une ligne par dépense. La catégorie se choisit dans la liste déroulante.
A4: Date | B4: Description | C4: Catégorie | D4: Montant | E4: Payé par
A5: 46328 | B5: Courses supermarché | C5: Courses alimentaires | D5: 87.4 | E5: Parent 1
A6: 46329 | B6: Paquet de couches | C6: Couches, hygiène, puériculture | D6: 18.9 | E6: Parent 2
A7: 46331 | B7: Loyer novembre | C7: Loyer / crédit immobilier | D7: 900 | E7: Compte commun

Sheet Tableau de bord
A1: Tableau de bord du mois
A3: =Paramètres!B4 -> 46327
A5: Total revenus | B5: =Paramètres!B14 -> 3450
A6: Total dépensé | B6: =SUM(Dépenses!$D$5:$D$304) -> 1006.3
A7: Reste à vivre (revenus − dépenses) | B7: =B5-B6 -> 2443.7
A8: Objectif d'épargne | B8: =Paramètres!B5 -> 150
A9: Objectif atteint ? | B9: =IF(B7>=B8,"Oui, bravo !","Pas encore") -> Oui, bravo !
A11: Catégorie | B11: Budget prévu | C11: Dépensé | D11: Reste | E11: % utilisé
A12: =IF(Paramètres!A17="","",Paramètres!A17) -> Loyer / crédit immobilier | B12: =IF(A12="","",Paramètres!B17) -> 900 | C12: =IF(A12="","",SUMIFS(Dépenses!$D$5:$D$304,Dépenses!$C$5:$C$304,A12)) -> 900 | D12: =IF(A12="","",B12-C12) -> 0 | E12: =IF(OR(A12="",N(B12)=0),"",C12/B12) -> 1
A13: =IF(Paramètres!A18="","",Paramètres!A18) -> Électricité, gaz, eau | B13: =IF(A13="","",Paramètres!B18) -> 140 | C13: =IF(A13="","",SUMIFS(Dépenses!$D$5:$D$304,Dépenses!$C$5:$C$304,A13)) -> 0 | D13: =IF(A13="","",B13-C13) -> 140 | E13: =IF(OR(A13="",N(B13)=0),"",C13/B13) -> 0
A14: =IF(Paramètres!A19="","",Paramètres!A19) -> Internet et téléphones | B14: =IF(A14="","",Paramètres!B19) -> 50 | C14: =IF(A14="","",SUMIFS(Dépenses!$D$5:$D$304,Dépenses!$C$5:$C$304,A14)) -> 0 | D14: =IF(A14="","",B14-C14) -> 50 | E14: =IF(OR(A14="",N(B14)=0),"",C14/B14) -> 0
A15: =IF(Paramètres!A20="","",Paramètres!A20) -> Assurances | B15: =IF(A15="","",Paramètres!B20) -> 80 | C15: =IF(A15="","",SUMIFS(Dépenses!$D$5:$D$304,Dépenses!$C$5:$C$304,A15)) -> 0 | D15: =IF(A15="","",B15-C15) -> 80 | E15: =IF(OR(A15="",N(B15)=0),"",C15/B15) -> 0
A16: =IF(Paramètres!A21="","",Paramètres!A21) -> Crèche / nounou / garde | B16: =IF(A16="","",Paramètres!B21) -> 250 | C16: =IF(A16="","",SUMIFS(Dépenses!$D$5:$D$304,Dépenses!$C$5:$C$304,A16)) -> 0 | D16: =IF(A16="","",B16-C16) -> 250 | E16: =IF(OR(A16="",N(B16)=0),"",C16/B16) -> 0
A17: =IF(Paramètres!A22="","",Paramètres!A22) -> Cantine et périscolaire | B17: =IF(A17="","",Paramètres!B22) -> 80 | C17: =IF(A17="","",SUMIFS(Dépenses!$D$5:$D$304,Dépenses!$C$5:$C$304,A17)) -> 0 | D17: =IF(A17="","",B17-C17) -> 80 | E17: =IF(OR(A17="",N(B17)=0),"",C17/B17) -> 0
A18: =IF(Paramètres!A23="","",Paramètres!A23) -> Courses alimentaires | B18: =IF(A18="","",Paramètres!B23) -> 550 | C18: =IF(A18="","",SUMIFS(Dépenses!$D$5:$D$304,Dépenses!$C$5:$C$304,A18)) -> 87.4 | D18: =IF(A18="","",B18-C18) -> 462.6 | E18: =IF(OR(A18="",N(B18)=0),"",C18/B18) -> 0.15890909
A19: =IF(Paramètres!A24="","",Paramètres!A24) -> Couches, hygiène, puériculture | B19: =IF(A19="","",Paramètres!B24) -> 60 | C19: =IF(A19="","",SUMIFS(Dépenses!$D$5:$D$304,Dépenses!$C$5:$C$304,A19)) -> 18.9 | D19: =IF(A19="","",B19-C19) -> 41.1 | E19: =IF(OR(A19="",N(B19)=0),"",C19/B19) -> 0.315
A20: =IF(Paramètres!A25="","",Paramètres!A25) -> Vêtements enfants | B20: =IF(A20="","",Paramètres!B25) -> 50 | C20: =IF(A20="","",SUMIFS(Dépenses!$D$5:$D$304,Dépenses!$C$5:$C$304,A20)) -> 0 | D20: =IF(A20="","",B20-C20) -> 50 | E20: =IF(OR(A20="",N(B20)=0),"",C20/B20) -> 0
A21: =IF(Paramètres!A26="","",Paramètres!A26) -> Activités et loisirs enfants | B21: =IF(A21="","",Paramètres!B26) -> 40 | C21: =IF(A21="","",SUMIFS(Dépenses!$D$5:$D$304,Dépenses!$C$5:$C$304,A21)) -> 0 | D21: =IF(A21="","",B21-C21) -> 40 | E21: =IF(OR(A21="",N(B21)=0),"",C21/B21) -> 0
A22: =IF(Paramètres!A27="","",Paramètres!A27) -> Santé / pharmacie | B22: =IF(A22="","",Paramètres!B27) -> 30 | C22: =IF(A22="","",SUMIFS(Dépenses!$D$5:$D$304,Dépenses!$C$5:$C$304,A22)) -> 0 | D22: =IF(A22="","",B22-C22) -> 30 | E22: =IF(OR(A22="",N(B22)=0),"",C22/B22) -> 0
A23: =IF(Paramètres!A28="","",Paramètres!A28) -> Transport / carburant | B23: =IF(A23="","",Paramètres!B28) -> 150 | C23: =IF(A23="","",SUMIFS(Dépenses!$D$5:$D$304,Dépenses!$C$5:$C$304,A23)) -> 0 | D23: =IF(A23="","",B23-C23) -> 150 | E23: =IF(OR(A23="",N(B23)=0),"",C23/B23) -> 0
... A31: =IF(Paramètres!A36="","",Paramètres!A36) | B31: =IF(A31="","",Paramètres!B36) | C31: =IF(A31="","",SUMIFS(Dépenses!$D$5:$D$304,Dépenses!$C$5:$C$304,A31)) | D31: =IF(A31="","",B31-C31) | E31: =IF(OR(A31="",N(B31)=0),"",C31/B31)
A32: Total | B32: =SUM(B12:B31) -> 2545 | C32: =SUM(C12:C31) -> 1006.3 | D32: =SUM(D12:D31) -> 1538.7 | E32: =IF(B32=0,"",C32/B32) -> 0.39540275
A33: Dépenses sans catégorie reconnue | C33: =B6-C32 -> 0
A35: Orange = 80 % du budget atteint · Rouge = budget dépassé

Sheet Défi 30 jours
A1: Défi 30 jours d'économies en famille
A2: Un petit geste par jour. Cochez « Oui » et notez l'économie estimée.
A4: Jour | B4: Défi du jour | C4: Réussi ? (Oui/Non) | D4: Économie estimée
A5: 1 | B5: Faire l'inventaire du frigo et des placards avant les courses
A6: 2 | B6: Préparer une liste de courses et s'y tenir
A7: 3 | B7: Repas « fond de placard » ce soir
A8: 4 | B8: Résilier ou suspendre un abonnement peu utilisé
A9: 5 | B9: Journée sans aucune dépense
A10: 6 | B10: Préparer le goûter des enfants maison
A11: 7 | B11: Comparer son forfait mobile et internet
A12: 8 | B12: Vendre un vêtement ou jouet trop petit (Vinted, Leboncoin)
A13: 9 | B13: Batch cooking : cuisiner 3 repas d'avance
A14: 10 | B14: Sortie gratuite en famille (parc, bibliothèque, balade)
A15: 11 | B15: Vérifier ses droits CAF sur caf.fr (simulateur)
A16: 12 | B16: Acheter en marque distributeur pour 5 produits
... A34: 30 | B34: Faire le bilan du défi en famille et fêter ça (gratuitement !)
B36: Jours réussis | D36: =COUNTIF(C5:C34,"Oui")&" / 30" -> 0 / 30
B37: Total économisé | D37: =SUM(D5:D34) -> 0
